copy_guardian/__init__.py
copy_guardian/copy_guardian.py
copy_guardian/copy_utils.py
copy_guardian-0.2.1.dist-info/AUTHORS.rst
copy_guardian-0.2.1.dist-info/LICENSE
copy_guardian-0.2.1.dist-info/METADATA
copy_guardian-0.2.1.dist-info/WHEEL
copy_guardian-0.2.1.dist-info/top_level.txt
copy_guardian-0.2.1.dist-info/RECORD
