Metadata-Version: 2.1
Name: copy_guardian
Version: 0.2.1
Summary: File system based semaphore + rsync
Author: Uwe
Author-email: uwe.schmitt@id.ethz.ch
License: MIT License
Project-URL: Source, https://cosmo-docs.phys.ethz.ch/copy_guardian
Classifier: Intended Audience :: Science/Research
Classifier: Intended Audience :: Developers
Classifier: License :: OSI Approved :: MIT License
Classifier: Natural Language :: English
Classifier: Programming Language :: Python :: 3
Classifier: Programming Language :: Python :: 3.9
Classifier: Programming Language :: Python :: 3.10
Classifier: Operating System :: OS Independent
Requires-Python: >=3.9
License-File: LICENSE
License-File: AUTHORS.rst
Requires-Dist: portalocker
Provides-Extra: dev
Requires-Dist: build ; extra == 'dev'
Requires-Dist: twine ; extra == 'dev'
Requires-Dist: pytest ; extra == 'dev'
Requires-Dist: pytest-cov ; extra == 'dev'
Requires-Dist: pytest-regtest ; extra == 'dev'
Requires-Dist: tox ; extra == 'dev'
Requires-Dist: flake8 ; extra == 'dev'
Requires-Dist: pre-commit ; extra == 'dev'
Requires-Dist: sphinx <7 ; extra == 'dev'
Requires-Dist: sphinx-pynpoint-theme ; extra == 'dev'
Requires-Dist: myst-parser ; extra == 'dev'
Provides-Extra: docs
Requires-Dist: sphinx <7 ; extra == 'docs'
Requires-Dist: sphinx-pynpoint-theme ; extra == 'docs'
Requires-Dist: myst-parser ; extra == 'docs'
